{
  "$schema": "https://raw.githubusercontent.com/spdx/spdx-spec/v2.2.1/schemas/spdx-schema.json",
  "spdxVersion": "SPDX-2.2",
  "dataLicense": "CC0-1.0",
  "SPDXID": "SPDXRef-DOCUMENT",
  "documentNamespace": "https://spdx.org/spdxdocs/libwebp-arm64-linux-1.5.0#1-83891c48-d5d0-4840-bf23-9f01e7c6b08f",
  "name": "libwebp:arm64-linux@1.5.0#1 8ae0cb807eb3512069f36124bbfb48168ac8050ddc99dc82345782959b8af789",
  "creationInfo": {
    "creators": [
      "Tool: vcpkg-2025-06-20-ef7c0d541124bbdd334a03467e7edb6c3364d199"
    ],
    "created": "2025-06-23T07:41:16Z"
  },
  "relationships": [
    {
      "spdxElementId": "SPDXRef-port",
      "relationshipType": "GENERATES",
      "relatedSpdxElement": "SPDXRef-binary"
    },
    {
      "spdxElementId": "SPDXRef-port",
      "relationshipType": "CONTAINS",
      "relatedSpdxElement": "SPDXRef-file-0"
    },
    {
      "spdxElementId": "SPDXRef-port",
      "relationshipType": "CONTAINS",
      "relatedSpdxElement": "SPDXRef-file-1"
    },
    {
      "spdxElementId": "SPDXRef-port",
      "relationshipType": "CONTAINS",
      "relatedSpdxElement": "SPDXRef-file-2"
    },
    {
      "spdxElementId": "SPDXRef-port",
      "relationshipType": "CONTAINS",
      "relatedSpdxElement": "SPDXRef-file-3"
    },
    {
      "spdxElementId": "SPDXRef-port",
      "relationshipType": "CONTAINS",
      "relatedSpdxElement": "SPDXRef-file-4"
    },
    {
      "spdxElementId": "SPDXRef-port",
      "relationshipType": "CONTAINS",
      "relatedSpdxElement": "SPDXRef-file-5"
    },
    {
      "spdxElementId": "SPDXRef-binary",
      "relationshipType": "GENERATED_FROM",
      "relatedSpdxElement": "SPDXRef-port"
    },
    {
      "spdxElementId": "SPDXRef-file-0",
      "relationshipType": "CONTAINED_BY",
      "relatedSpdxElement": "SPDXRef-port"
    },
    {
      "spdxElementId": "SPDXRef-file-1",
      "relationshipType": "CONTAINED_BY",
      "relatedSpdxElement": "SPDXRef-port"
    },
    {
      "spdxElementId": "SPDXRef-file-2",
      "relationshipType": "CONTAINED_BY",
      "relatedSpdxElement": "SPDXRef-port"
    },
    {
      "spdxElementId": "SPDXRef-file-3",
      "relationshipType": "CONTAINED_BY",
      "relatedSpdxElement": "SPDXRef-port"
    },
    {
      "spdxElementId": "SPDXRef-file-4",
      "relationshipType": "CONTAINED_BY",
      "relatedSpdxElement": "SPDXRef-port"
    },
    {
      "spdxElementId": "SPDXRef-file-5",
      "relationshipType": "CONTAINED_BY",
      "relatedSpdxElement": "SPDXRef-port"
    },
    {
      "spdxElementId": "SPDXRef-file-5",
      "relationshipType": "DEPENDENCY_MANIFEST_OF",
      "relatedSpdxElement": "SPDXRef-port"
    }
  ],
  "packages": [
    {
      "name": "libwebp",
      "SPDXID": "SPDXRef-port",
      "versionInfo": "1.5.0#1",
      "downloadLocation": "git+https://github.com/Microsoft/vcpkg#ports/libwebp",
      "homepage": "https://github.com/webmproject/libwebp",
      "licenseConcluded": "BSD-3-Clause",
      "licenseDeclared": "NOASSERTION",
      "copyrightText": "NOASSERTION",
      "description": "WebP codec: library to encode and decode images in WebP format",
      "comment": "This is the port (recipe) consumed by vcpkg."
    },
    {
      "name": "libwebp:arm64-linux",
      "SPDXID": "SPDXRef-binary",
      "versionInfo": "8ae0cb807eb3512069f36124bbfb48168ac8050ddc99dc82345782959b8af789",
      "downloadLocation": "NONE",
      "licenseConcluded": "BSD-3-Clause",
      "licenseDeclared": "NOASSERTION",
      "copyrightText": "NOASSERTION",
      "comment": "This is a binary package built by vcpkg."
    },
    {
      "SPDXID": "SPDXRef-resource-0",
      "name": "webmproject/libwebp",
      "downloadLocation": "git+https://github.com/webmproject/libwebp@v1.5.0",
      "licenseConcluded": "NOASSERTION",
      "licenseDeclared": "NOASSERTION",
      "copyrightText": "NOASSERTION",
      "checksums": [
        {
          "algorithm": "SHA512",
          "checksumValue": "a922cb84e147f1aeaaac9ff4c6000ebad067a9a4b74d94c25d6c9181f487dfd6d8c7966ac1d239f4fad65cc07ad3d5c82ee9ab4adfa4b125d231056781632548"
        }
      ]
    }
  ],
  "files": [
    {
      "fileName": "./0002-cmake-config.patch",
      "SPDXID": "SPDXRef-file-0",
      "checksums": [
        {
          "algorithm": "SHA256",
          "checksumValue": "55567849c38d3231032cb0aff6c067e1e2ca1c6515823880a6c4a885780c0ba3"
        }
      ],
      "licenseConcluded": "NOASSERTION",
      "copyrightText": "NOASSERTION"
    },
    {
      "fileName": "./0003-simd.patch",
      "SPDXID": "SPDXRef-file-1",
      "checksums": [
        {
          "algorithm": "SHA256",
          "checksumValue": "4ca73353afbfefc31147d62d7f035e151b981f9cda6636151a84a3ca51cd39d9"
        }
      ],
      "licenseConcluded": "NOASSERTION",
      "copyrightText": "NOASSERTION"
    },
    {
      "fileName": "./usage",
      "SPDXID": "SPDXRef-file-2",
      "checksums": [
        {
          "algorithm": "SHA256",
          "checksumValue": "4898bdd3351dcd0868d2f0786ab114c8b161dda8db6cd84f7fe93bf0639f08d1"
        }
      ],
      "licenseConcluded": "NOASSERTION",
      "copyrightText": "NOASSERTION"
    },
    {
      "fileName": "./0008-sdl.patch",
      "SPDXID": "SPDXRef-file-3",
      "checksums": [
        {
          "algorithm": "SHA256",
          "checksumValue": "2f05c20f07165ac556ef7c67c25af0e461d3cbd8539d5769296ace52b37b9311"
        }
      ],
      "licenseConcluded": "NOASSERTION",
      "copyrightText": "NOASSERTION"
    },
    {
      "fileName": "./portfile.cmake",
      "SPDXID": "SPDXRef-file-4",
      "checksums": [
        {
          "algorithm": "SHA256",
          "checksumValue": "651dcac16db26c84ae4b7e2212d50069e03f23e109dd8305f81aa35293c1fbf6"
        }
      ],
      "licenseConcluded": "NOASSERTION",
      "copyrightText": "NOASSERTION"
    },
    {
      "fileName": "./vcpkg.json",
      "SPDXID": "SPDXRef-file-5",
      "checksums": [
        {
          "algorithm": "SHA256",
          "checksumValue": "947caa1503b7f70b846f045ad40868189ab2eecdf7c4da24fe459bc3805d0139"
        }
      ],
      "licenseConcluded": "NOASSERTION",
      "copyrightText": "NOASSERTION"
    }
  ]
}
